uipath_connectors/google_sheets/__init__.py
uipath_connectors/google_sheets/client.py
uipath_connectors/google_sheets/errors.py
uipath_connectors/google_sheets/py.typed
uipath_connectors/google_sheets/types.py
uipath_connectors/google_sheets/api/__init__.py
uipath_connectors/google_sheets/api/add_sheet/__init__.py
uipath_connectors/google_sheets/api/add_sheet/add_sheet.py
uipath_connectors/google_sheets/api/create_spreadsheet/__init__.py
uipath_connectors/google_sheets/api/create_spreadsheet/create_spreadsheet.py
uipath_connectors/google_sheets/api/delete_sheet/__init__.py
uipath_connectors/google_sheets/api/delete_sheet/delete_sheet.py
uipath_connectors/google_sheets/api/rename_sheet/__init__.py
uipath_connectors/google_sheets/api/rename_sheet/rename_sheet.py
uipath_connectors/google_sheets/models/__init__.py
uipath_connectors/google_sheets/models/add_sheet_request.py
uipath_connectors/google_sheets/models/add_sheet_request_add_sheet.py
uipath_connectors/google_sheets/models/add_sheet_request_add_sheet_properties.py
uipath_connectors/google_sheets/models/add_sheet_request_add_sheet_properties_grid_properties.py
uipath_connectors/google_sheets/models/add_sheet_response.py
uipath_connectors/google_sheets/models/add_sheet_response_replies_add_sheet.py
uipath_connectors/google_sheets/models/add_sheet_response_replies_add_sheet_properties.py
uipath_connectors/google_sheets/models/add_sheet_response_replies_add_sheet_properties_grid_properties.py
uipath_connectors/google_sheets/models/add_sheet_response_replies_array_item_ref.py
uipath_connectors/google_sheets/models/create_spreadsheet_request.py
uipath_connectors/google_sheets/models/create_spreadsheet_response.py
uipath_connectors/google_sheets/models/create_spreadsheet_response_properties.py
uipath_connectors/google_sheets/models/create_spreadsheet_response_properties_default_format.py
uipath_connectors/google_sheets/models/create_spreadsheet_response_properties_default_format_background_color.py
uipath_connectors_google_sheets-1.8.16.dev12.dist-info/METADATA
uipath_connectors_google_sheets-1.8.16.dev12.dist-info/WHEEL
uipath_connectors_google_sheets-1.8.16.dev12.dist-info/entry_points.txt
uipath_connectors_google_sheets-1.8.16.dev12.dist-info/top_level.txt
uipath_connectors_google_sheets-1.8.16.dev12.dist-info/RECORD
